producesyntaxed.py
producesyntaxed-1.2.0.dist-info/LICENCE
producesyntaxed-1.2.0.dist-info/METADATA
producesyntaxed-1.2.0.dist-info/WHEEL
producesyntaxed-1.2.0.dist-info/RECORD
